BmpLib_Ai/__init__.py
BmpLib_Ai/bmp_func.py
BmpLib_Ai-0.0.30.dist-info/LICENSE
BmpLib_Ai-0.0.30.dist-info/METADATA
BmpLib_Ai-0.0.30.dist-info/WHEEL
BmpLib_Ai-0.0.30.dist-info/top_level.txt
BmpLib_Ai-0.0.30.dist-info/RECORD
