Metadata-Version: 2.2
Name: BmpLib_Ai
Version: 0.0.30
Summary: This package implements all the logic of Brief My Press.AI
Author-email: OUEDRAOGO Taoufiq <taoufiq.ouedraogo@icloud.com>
License: Copyright (c) 2018 The Python Packaging Authority
Project-URL: Homepage, https://github.com/Taoufiq-Ouedraogo/Brief-My-Press-AI-Library
Classifier: Programming Language :: Python :: 3
Classifier: Operating System :: OS Independent
Requires-Python: <3.11,>=3.10
License-File: LICENSE
Requires-Dist: setuptools
Requires-Dist: tensorflow==2.18.0
Requires-Dist: keras==3.8.0
Requires-Dist: transformers
Requires-Dist: spacy
Requires-Dist: click==8.1.7
Requires-Dist: requests==2.31.0
Requires-Dist: certifi==2024.12.14
Requires-Dist: idna==3.10
Requires-Dist: colorama==0.4.6
Requires-Dist: charset-normalizer==3.4.1
Requires-Dist: gTTS==2.5.3
Requires-Dist: mlx-lm
